package_name/__init__.py
package_name/some_file.py
python_repo_structure-0.1.1.dist-info/LICENSE
python_repo_structure-0.1.1.dist-info/WHEEL
python_repo_structure-0.1.1.dist-info/METADATA
python_repo_structure-0.1.1.dist-info/RECORD
