Metadata-Version: 2.1
Name: python-repo-structure
Version: 0.1.1
Summary: Show how to structure small Python package using CI (Codecov) and Poetry to upload to PyPi.
Home-page: https://github.com/dimitryzub/python-repo-structure
License: MIT
Author: Dimitry Zub
Author-email: dimitryzub@gmail.com
Requires-Python: >=3.8,<4.0
Classifier: Intended Audience :: Developers
Classifier: License :: OSI Approved :: MIT License
Classifier: Operating System :: MacOS
Classifier: Operating System :: Microsoft :: Windows
Classifier: Operating System :: POSIX :: Linux
Classifier: Programming Language :: Python :: 3
Classifier: Programming Language :: Python :: 3.6
Classifier: Programming Language :: Python :: 3.7
Classifier: Programming Language :: Python :: 3.8
Classifier: Programming Language :: Python :: 3.9
